langflow_install/__init__.py
langflow_install/langflow_install.py
langflow_install-0.1.1.dist-info/METADATA
langflow_install-0.1.1.dist-info/WHEEL
langflow_install-0.1.1.dist-info/entry_points.txt
langflow_install-0.1.1.dist-info/top_level.txt
langflow_install-0.1.1.dist-info/RECORD
