Metadata-Version: 2.2
Name: langflow-install
Version: 0.1.1
Summary: Simple langflow installer powered by uv
Requires-Python: >=3.12
Requires-Dist: uv>=0.5.24
